pyfiction/__init__.py
pyfiction/agents/__init__.py
pyfiction/agents/agent.py
pyfiction/agents/random_agent.py
pyfiction/agents/ssaqn_agent.py
pyfiction/games/__init__.py
pyfiction/games/game.py
pyfiction/games/CatSimulator2016/__init__.py
pyfiction/games/CatSimulator2016/cat_simulator_2016.py
pyfiction/games/CatSimulator2016/index.html
pyfiction/games/ChildsPlay/__init__.py
pyfiction/games/HowlingDogs/__init__.py
pyfiction/games/HowlingDogs/howling_dogs.py
pyfiction/games/HowlingDogs/index.html
pyfiction/games/MachineOfDeath/__init__.py
pyfiction/games/MachineOfDeath/machine_of_death.py
pyfiction/games/SavingJohn/__init__.py
pyfiction/games/SavingJohn/saving_john.py
pyfiction/games/Six/Six.gblorb
pyfiction/games/Six/__init__.py
pyfiction/games/Six/six.py
pyfiction/games/StarCourt/__init__.py
pyfiction/games/StarCourt/index.html
pyfiction/games/StarCourt/star_court.py
pyfiction/games/TheRedHair/__init__.py
pyfiction/games/TheRedHair/index.html
pyfiction/games/TheRedHair/the_red_hair.py
pyfiction/games/TheRedHair/index_files/jquery.js
pyfiction/games/TheRedHair/index_files/story.js
pyfiction/games/TheRedHair/index_files/style.css
pyfiction/games/Transit/__init__.py
pyfiction/games/Transit/index.html
pyfiction/games/Transit/transit.py
pyfiction/interpreters/__init__.py
pyfiction/interpreters/interpreter.py
pyfiction/interpreters/glulx/__init__.py
pyfiction/interpreters/glulx/cheapglulxe
pyfiction/interpreters/glulx/glulxe.py
pyfiction/interpreters/zmachine/dfrotz
pyfiction/simulators/__init__.py
pyfiction/simulators/glulx_simulator.py
pyfiction/simulators/html_simulator.py
pyfiction/simulators/nbstreamreader.py
pyfiction/simulators/simulator.py
pyfiction/simulators/zmachine_simulator.py
pyfiction/simulators/games/__init__.py
pyfiction/simulators/games/catsimulator2016_simulator.py
pyfiction/simulators/games/howlingdogs_simulator.py
pyfiction/simulators/games/machineofdeath_simulator.py
pyfiction/simulators/games/savingjohn_simulator.py
pyfiction-0.1.3.dist-info/LICENSE
pyfiction-0.1.3.dist-info/METADATA
pyfiction-0.1.3.dist-info/WHEEL
pyfiction-0.1.3.dist-info/entry_points.txt
pyfiction-0.1.3.dist-info/top_level.txt
pyfiction-0.1.3.dist-info/RECORD
