Metadata-Version: 2.1
Name: pyfiction
Version: 0.1.3
Summary: pyfiction, a universal API for text-based games
Home-page: https://github.com/MikulasZelinka/pyfiction
Author: Mikuláš Zelinka
License: MIT
Keywords: pyfiction text games interactive fiction gym
Platform: UNKNOWN
Classifier: Development Status :: 3 - Alpha
Classifier: Intended Audience :: Science/Research
Classifier: Topic :: Scientific/Engineering :: Artificial Intelligence
Classifier: License :: OSI Approved :: MIT License
Classifier: Programming Language :: Python :: 3.6
License-File: LICENSE
Requires-Dist: numpy
Requires-Dist: tensorflow (==2.5.3)
Requires-Dist: keras (==2.0.4)
Requires-Dist: h5py
Requires-Dist: selenium
Requires-Dist: pydot
